<?xml version="1.0" encoding="utf-8"?>
<!DOCTYPE hibernate-mapping PUBLIC "-//Hibernate/Hibernate Mapping DTD 3.0//EN"
"http://hibernate.sourceforge.net/hibernate-mapping-3.0.dtd">
<hibernate-mapping>
	<class name="cc.natapp4.ddaig.domain.User">
		<id name="uid" length="50">
			<!-- 设置主键产生器为uuid，则我们无需手动为持久化类的主键属性赋值，则hibernate会自动产生uuid码填充该属性及其在数据库所对应的字段 -->
			<!-- 设置主键产生器是assigned，是由于需要根据用户的uid来生成qrcode，因此需要手动创建uid -->
			<generator class="assigned"></generator>
		</id>
		<property name="openid" length="50"></property>
		<property name="cardid" length="20"></property>
		<property name="username" length="20"></property>
		<property name="sickname" length="20"></property>
		<property name="registrationTime" type="long"></property>
		<property name="address" length="100"></property>
		<property name="serveTime" type="long"></property>
		<property name="email" length="50"></property>
		<property name="score" type="integer"></property>
		<property name="sex" length="6"></property>
		<property name="birth" length="12"></property>
		<property name="age" type="integer"></property>
		<property name="phone" length="20"></property>
		<property name="qrcode" length="100"></property>
		<property name="ishere" type="true_false"></property>
		<property name="locked" type="true_false"></property>

		<many-to-one name="grouping" column="gid"
			class="cc.natapp4.ddaig.domain.Grouping" cascade="save-update" lazy="false">
		</many-to-one>

		<list name="visits"  cascade="save-update" lazy="true">
			<key  column="uid"></key>
			<list-index column="index4user"></list-index>
			<one-to-many class="cc.natapp4.ddaig.domain.Visitor" />
		</list>

		<set name="exchanges" cascade="save-update" lazy="true">
			<key>
				<column name="uid"></column>
			</key>
			<one-to-many class="cc.natapp4.ddaig.domain.Exchange" />
		</set>

		<!-- 一对一的关键就是借助unique=true实现manager、member表外键的唯一性 -->
		<one-to-one name="manager" cascade="all" fetch="join"   lazy="false"
			class="cc.natapp4.ddaig.domain.Manager"></one-to-one>
		<one-to-one name="member" cascade="all" fetch="join"   lazy="false"
			class="cc.natapp4.ddaig.domain.Member"></one-to-one>


	</class>
</hibernate-mapping>